neuronmodels/__init__.py
neuronmodels/neuronmodels.py
neuronmodels-0.0.1.dist-info/METADATA
neuronmodels-0.0.1.dist-info/WHEEL
neuronmodels-0.0.1.dist-info/top_level.txt
neuronmodels-0.0.1.dist-info/RECORD
